setup.py
matryoshka/__init__.py
matryoshka/matryoshka.py
matryoshka/test.py
matryoshka.egg-info/PKG-INFO
matryoshka.egg-info/SOURCES.txt
matryoshka.egg-info/dependency_links.txt
matryoshka.egg-info/requires.txt
matryoshka.egg-info/top_level.txt