Metadata-Version: 1.0
Name: matryoshka
Version: 0.0.3
Summary: To cut small images from a original image in batch, just like the Matryoshka Dolls.
Home-page: UNKNOWN
Author: JackyShen
Author-email: mebusw@gmail.com
License: MIT License
Keywords: matryoshka,icon
Platform: any
